storefront_api_views_product/__init__.py
storefront_api_views_product/detail_view_factory.py
storefront_api_views_product/errors.py
storefront_api_views_product/py.typed
storefront_api_views_product/summary_view_factory.py
storefront_api_views_product/facades/__init__.py
storefront_api_views_product/facades/badges.py
storefront_api_views_product/facades/buybox_preference.py
storefront_api_views_product/utils/__init__.py
storefront_api_views_product/utils/text.py
storefront_api_views_product/views/__init__.py
storefront_api_views_product/views/badges.py
storefront_api_views_product/views/buybox.py
storefront_api_views_product/views/core.py
storefront_api_views_product/views/enhanced_ecommerce.py
storefront_api_views_product/views/gallery.py
storefront_api_views_product/views/google_structured_data.py
storefront_api_views_product/views/models.py
storefront_api_views_product/views/promotions.py
storefront_api_views_product/views/reviews.py
storefront_api_views_product/views/stock_availability.py
storefront_api_views_product/views/variant.py
tests/__init__.py
tests/conftest.py
tests/test_detail_view_factory.py
tests/test_summary_view_factory.py
tests/facades/__init__.py
tests/facades/cases_badges.py
tests/facades/conftest.py
tests/facades/test_badges.py
tests/facades/test_buybox_preference.py
tests/utils/__init__.py
tests/utils/test_text.py
tests/views/__init__.py
tests/views/cases_badges.py
tests/views/conftest.py
tests/views/test_badges.py
tests/views/test_buybox_detail.py
tests/views/test_buybox_summary.py
tests/views/test_core.py
tests/views/test_enhanced_ecommerce.py
tests/views/test_gallery.py
tests/views/test_google_structured_data.py
tests/views/test_models.py
tests/views/test_promotions_summary.py
tests/views/test_reviews_summary.py
tests/views/test_stock_availability_summary.py
tests/views/test_variant_summary.py
storefront_api_views_product-2.0.2.dist-info/METADATA
storefront_api_views_product-2.0.2.dist-info/WHEEL
storefront_api_views_product-2.0.2.dist-info/top_level.txt
storefront_api_views_product-2.0.2.dist-info/RECORD
