Metadata-Version: 2.1
Name: storefront-api-views-product
Version: 2.0.2
Home-page: https://github.com/TAKEALOT/storefront-api-views-product
Author: DSCBE
Author-email: en-dsc-be@takealot.com
Classifier: Programming Language :: Python :: 3
Classifier: Natural Language :: English
Classifier: Intended Audience :: Developers
Requires-Dist: typing-extensions
Requires-Dist: storefront-product-adapter >=2.0.0
Requires-Dist: storefront-media-urls >=1.0.0
Provides-Extra: dev
Requires-Dist: pytest <8.0.0 ; extra == 'dev'
Requires-Dist: pytest-cov ; extra == 'dev'
Requires-Dist: pytest-mock ; extra == 'dev'
Requires-Dist: pytest-cases ; extra == 'dev'
Requires-Dist: pytest-randomly ; extra == 'dev'
Requires-Dist: freezegun ; extra == 'dev'
Requires-Dist: pre-commit ; extra == 'dev'
Requires-Dist: flake8 ; extra == 'dev'
Requires-Dist: flake8-comprehensions ; extra == 'dev'
Requires-Dist: flake8-mutable ; extra == 'dev'
Requires-Dist: mypy ; extra == 'dev'
Requires-Dist: black ; extra == 'dev'
Requires-Dist: isort ; extra == 'dev'
Requires-Dist: types-setuptools ; extra == 'dev'
Requires-Dist: wheel ; extra == 'dev'
